bartesdk/__init__.py
bartesdk/base.py
bartesdk/buyers.py
bartesdk/charges.py
bartesdk/orders.py
bartesdk/paymentlinks.py
bartesdk/plans.py
bartesdk/subscriptions.py
bartesdk/subseller.py
BarteSDK-1.0.12.dist-info/LICENSE
BarteSDK-1.0.12.dist-info/METADATA
BarteSDK-1.0.12.dist-info/WHEEL
BarteSDK-1.0.12.dist-info/top_level.txt
BarteSDK-1.0.12.dist-info/RECORD
